config_suraj/__init__.py
config_suraj/configuration.py
config_suraj-0.5.dist-info/METADATA
config_suraj-0.5.dist-info/RECORD
config_suraj-0.5.dist-info/WHEEL
config_suraj-0.5.dist-info/top_level.txt
