Metadata-Version: 2.1
Name: config-suraj
Version: 0.5
Summary: using oslo_config template to create configuration to register
Home-page: https://github.com/SURAJTHEGREAT/config.git
Author: Suraj
Author-email: suraj.iot257@gmail.com
License: Apache License (2.0)
Download-URL: https://github.com/SURAJTHEGREAT/config.git
Platform: UNKNOWN
Classifier: Development Status :: 3 - Alpha
Classifier: License :: OSI Approved :: Apache Software License
Classifier: Programming Language :: Python
Classifier: Programming Language :: Python :: 2
Classifier: Programming Language :: Python :: 2.7
Classifier: Programming Language :: Python :: 3
Classifier: Programming Language :: Python :: 3.4
Classifier: Intended Audience :: Developers
Classifier: Environment :: Console
Requires-Dist: oslo-config
Requires-Dist: log-suraj
